ai/backend/appproxy/worker/VERSION
ai/backend/appproxy/worker/__init__.py
ai/backend/appproxy/worker/config.py
ai/backend/appproxy/worker/coordinator_client.py
ai/backend/appproxy/worker/metrics.py
ai/backend/appproxy/worker/py.typed
ai/backend/appproxy/worker/server.py
ai/backend/appproxy/worker/types.py
ai/backend/appproxy/worker/api/health.py
ai/backend/appproxy/worker/api/setup.py
ai/backend/appproxy/worker/cli/__main__.py
ai/backend/appproxy/worker/cli/config.py
ai/backend/appproxy/worker/cli/context.py
ai/backend/appproxy/worker/cli/dependencies.py
ai/backend/appproxy/worker/cli/health.py
ai/backend/appproxy/worker/cli/start_server.py
ai/backend/appproxy/worker/dependencies/__init__.py
ai/backend/appproxy/worker/dependencies/composer.py
ai/backend/appproxy/worker/dependencies/bootstrap/__init__.py
ai/backend/appproxy/worker/dependencies/bootstrap/composer.py
ai/backend/appproxy/worker/dependencies/bootstrap/config.py
ai/backend/appproxy/worker/dependencies/infrastructure/__init__.py
ai/backend/appproxy/worker/dependencies/infrastructure/composer.py
ai/backend/appproxy/worker/dependencies/infrastructure/redis.py
ai/backend/appproxy/worker/errors/__init__.py
ai/backend/appproxy/worker/errors/circuit.py
ai/backend/appproxy/worker/errors/config.py
ai/backend/appproxy/worker/errors/process.py
ai/backend/appproxy/worker/proxy/backend/__init__.py
ai/backend/appproxy/worker/proxy/backend/base.py
ai/backend/appproxy/worker/proxy/backend/h2.py
ai/backend/appproxy/worker/proxy/backend/http.py
ai/backend/appproxy/worker/proxy/backend/tcp.py
ai/backend/appproxy/worker/proxy/backend/traefik.py
ai/backend/appproxy/worker/proxy/frontend/__init__.py
ai/backend/appproxy/worker/proxy/frontend/base.py
ai/backend/appproxy/worker/proxy/frontend/tcp.py
ai/backend/appproxy/worker/proxy/frontend/traefik.py
ai/backend/appproxy/worker/proxy/frontend/h2/base.py
ai/backend/appproxy/worker/proxy/frontend/h2/port.py
ai/backend/appproxy/worker/proxy/frontend/h2/subdomain.py
backend_ai_appproxy_worker-26.1.0.dist-info/METADATA
backend_ai_appproxy_worker-26.1.0.dist-info/WHEEL
backend_ai_appproxy_worker-26.1.0.dist-info/entry_points.txt
backend_ai_appproxy_worker-26.1.0.dist-info/namespace_packages.txt
backend_ai_appproxy_worker-26.1.0.dist-info/top_level.txt
backend_ai_appproxy_worker-26.1.0.dist-info/RECORD
